sklearnsk/__init__.py
sklearnsk/core.py
sklearnsk/eval.py
sklearnsk/helpers.py
sklearnsk/tests/__init__.py
sklearnsk/tests/test_metrics.py
sklearnsk-0.1.4.dist-info/DESCRIPTION.rst
sklearnsk-0.1.4.dist-info/METADATA
sklearnsk-0.1.4.dist-info/RECORD
sklearnsk-0.1.4.dist-info/WHEEL
sklearnsk-0.1.4.dist-info/entry_points.txt
sklearnsk-0.1.4.dist-info/metadata.json
sklearnsk-0.1.4.dist-info/top_level.txt
