Metadata-Version: 2.0
Name: sklearnsk
Version: 0.1.4
Summary: A wrapper for sklearn, that makes it easier to write, tune and evaluate classification and regression systems
Home-page: https://gitlab.com/sidekicklabs/sklearn-sidekick
Author: David Milne
Author-email: d.n.milne@gmail.com
License: MIT
Keywords: machinelearning sklearn
Platform: UNKNOWN
Classifier: Development Status :: 3 - Alpha
Classifier: Intended Audience :: Developers
Classifier: Topic :: Scientific/Engineering :: Artificial Intelligence
Classifier: License :: OSI Approved :: MIT License
Classifier: Programming Language :: Python :: 3
Classifier: Programming Language :: Python :: 3.3
Classifier: Programming Language :: Python :: 3.4
Classifier: Programming Language :: Python :: 3.5
Provides-Extra: test
Provides-Extra: dev
Requires-Dist: numpy
Requires-Dist: scipy
Requires-Dist: sklearn
Requires-Dist: tqdm
Provides-Extra: dev
Requires-Dist: check-manifest; extra == 'dev'
Provides-Extra: test
Requires-Dist: coverage; extra == 'test'
